{"name":"Chelsea Knight","stravaId":"","parkrunId":"145938","parkrunRunList":[{"event":"Itchen Valley Country","date":"2023-12-30T00:00:00","eventNo":131,"position":116,"raceTime":"00:41:08","ageGrading":36.79,"pb":true},{"event":"Rushmoor","date":"2023-12-23T00:00:00","eventNo":392,"position":370,"raceTime":"00:35:38","ageGrading":42.47,"pb":true},{"event":"Rushmoor","date":"2023-12-02T00:00:00","eventNo":389,"position":187,"raceTime":"00:28:29","ageGrading":53.13,"pb":true},{"event":"Rushmoor","date":"2022-09-10T00:00:00","eventNo":333,"position":239,"raceTime":"00:28:47","ageGrading":52.29,"pb":true},{"event":"Rushmoor","date":"2022-08-27T00:00:00","eventNo":331,"position":276,"raceTime":"00:35:46","ageGrading":42.08,"pb":true},{"event":"Frimley Lodge","date":"2022-05-07T00:00:00","eventNo":568,"position":377,"raceTime":"00:30:53","ageGrading":48.73,"pb":true},{"event":"Rushmoor","date":"2022-04-30T00:00:00","eventNo":322,"position":355,"raceTime":"00:41:55","ageGrading":35.90,"pb":true},{"event":"Rushmoor","date":"2022-04-16T00:00:00","eventNo":320,"position":257,"raceTime":"00:31:24","ageGrading":47.93,"pb":true},{"event":"Rushmoor","date":"2022-04-09T00:00:00","eventNo":319,"position":299,"raceTime":"00:34:50","ageGrading":43.21,"pb":true},{"event":"Frimley Lodge","date":"2022-03-05T00:00:00","eventNo":559,"position":347,"raceTime":"00:43:21","ageGrading":34.72,"pb":true},{"event":"Frimley Lodge","date":"2021-11-13T00:00:00","eventNo":544,"position":283,"raceTime":"00:33:17","ageGrading":45.07,"pb":true},{"event":"Henderson Lake","date":"2021-10-02T00:00:00","eventNo":62,"position":31,"raceTime":"00:56:43","ageGrading":26.45,"pb":true},{"event":"Rushmoor","date":"2020-02-15T00:00:00","eventNo":283,"position":233,"raceTime":"00:27:31","ageGrading":54.33,"pb":true},{"event":"Rushmoor","date":"2020-02-08T00:00:00","eventNo":282,"position":352,"raceTime":"00:29:16","ageGrading":51.08,"pb":true},{"event":"Frimley Lodge","date":"2020-02-01T00:00:00","eventNo":521,"position":203,"raceTime":"00:27:19","ageGrading":54.73,"pb":true},{"event":"Frimley Lodge","date":"2020-01-11T00:00:00","eventNo":518,"position":463,"raceTime":"00:34:25","ageGrading":43.29,"pb":true},{"event":"Rushmoor","date":"2019-12-14T00:00:00","eventNo":272,"position":133,"raceTime":"00:25:46","ageGrading":57.83,"pb":true},{"event":"Sandhurst Memorial","date":"2019-12-07T00:00:00","eventNo":1,"position":227,"raceTime":"00:30:39","ageGrading":48.61,"pb":true},{"event":"Frimley Lodge","date":"2019-11-30T00:00:00","eventNo":510,"position":89,"raceTime":"00:24:11","ageGrading":61.61,"pb":true},{"event":"Frimley Lodge","date":"2019-11-23T00:00:00","eventNo":509,"position":141,"raceTime":"00:25:18","ageGrading":58.89,"pb":true},{"event":"Frimley Lodge","date":"2019-11-16T00:00:00","eventNo":508,"position":193,"raceTime":"00:26:53","ageGrading":55.42,"pb":true},{"event":"California Country","date":"2019-11-09T00:00:00","eventNo":38,"position":33,"raceTime":"00:24:29","ageGrading":60.86,"pb":true},{"event":"Frimley Lodge","date":"2019-10-26T00:00:00","eventNo":505,"position":223,"raceTime":"00:29:44","ageGrading":50.11,"pb":true},{"event":"Frimley Lodge","date":"2019-10-05T00:00:00","eventNo":502,"position":505,"raceTime":"00:41:57","ageGrading":35.52,"pb":true},{"event":"Frimley Lodge","date":"2019-09-28T00:00:00","eventNo":501,"position":632,"raceTime":"00:40:59","ageGrading":36.36,"pb":true},{"event":"Frimley Lodge","date":"2019-09-14T00:00:00","eventNo":499,"position":216,"raceTime":"00:27:21","ageGrading":54.48,"pb":true},{"event":"California Country","date":"2019-07-20T00:00:00","eventNo":22,"position":128,"raceTime":"00:33:13","ageGrading":44.86,"pb":true},{"event":"Rushmoor","date":"2019-07-13T00:00:00","eventNo":251,"position":210,"raceTime":"00:31:43","ageGrading":46.98,"pb":true},{"event":"Rushmoor","date":"2019-07-06T00:00:00","eventNo":250,"position":167,"raceTime":"00:26:10","ageGrading":56.94,"pb":true},{"event":"Frimley Lodge","date":"2019-06-29T00:00:00","eventNo":489,"position":484,"raceTime":"00:33:49","ageGrading":44.06,"pb":true},{"event":"Frimley Lodge","date":"2019-06-01T00:00:00","eventNo":485,"position":216,"raceTime":"00:26:33","ageGrading":56.12,"pb":true},{"event":"Frimley Lodge","date":"2019-05-04T00:00:00","eventNo":482,"position":521,"raceTime":"00:37:22","ageGrading":39.88,"pb":true},{"event":"Guildford","date":"2019-04-13T00:00:00","eventNo":349,"position":385,"raceTime":"00:30:23","ageGrading":49.04,"pb":true},{"event":"Bracknell","date":"2019-04-06T00:00:00","eventNo":213,"position":254,"raceTime":"00:35:24","ageGrading":42.09,"pb":true},{"event":"Frimley Lodge","date":"2019-03-30T00:00:00","eventNo":477,"position":418,"raceTime":"00:34:43","ageGrading":42.92,"pb":true},{"event":"Frimley Lodge","date":"2019-03-23T00:00:00","eventNo":476,"position":174,"raceTime":"00:25:44","ageGrading":57.90,"pb":true},{"event":"Frimley Lodge","date":"2019-03-16T00:00:00","eventNo":475,"position":342,"raceTime":"00:32:40","ageGrading":45.61,"pb":true},{"event":"Frimley Lodge","date":"2019-03-09T00:00:00","eventNo":474,"position":151,"raceTime":"00:25:50","ageGrading":57.68,"pb":true},{"event":"Frimley Lodge","date":"2019-02-23T00:00:00","eventNo":472,"position":416,"raceTime":"00:32:41","ageGrading":45.59,"pb":true},{"event":"Frimley Lodge","date":"2019-02-09T00:00:00","eventNo":470,"position":240,"raceTime":"00:28:04","ageGrading":53.09,"pb":true},{"event":"Frimley Lodge","date":"2019-02-02T00:00:00","eventNo":469,"position":284,"raceTime":"00:38:01","ageGrading":39.19,"pb":true},{"event":"Frimley Lodge","date":"2019-01-26T00:00:00","eventNo":468,"position":454,"raceTime":"00:36:51","ageGrading":40.34,"pb":true},{"event":"Didcot","date":"2019-01-19T00:00:00","eventNo":198,"position":172,"raceTime":"00:31:46","ageGrading":46.80,"pb":true},{"event":"Rushmoor","date":"2019-01-12T00:00:00","eventNo":230,"position":489,"raceTime":"00:33:24","ageGrading":44.51,"pb":true},{"event":"Frimley Lodge","date":"2019-01-05T00:00:00","eventNo":465,"position":637,"raceTime":"00:54:46","ageGrading":27.15,"pb":true},{"event":"Frimley Lodge","date":"2019-01-01T00:00:00","eventNo":464,"position":741,"raceTime":"00:56:13","ageGrading":26.45,"pb":true},{"event":"Frimley Lodge","date":"2018-12-29T00:00:00","eventNo":463,"position":457,"raceTime":"00:57:59","ageGrading":25.64,"pb":true},{"event":"Frimley Lodge","date":"2018-11-24T00:00:00","eventNo":457,"position":346,"raceTime":"00:34:15","ageGrading":43.41,"pb":true},{"event":"Frimley Lodge","date":"2018-11-17T00:00:00","eventNo":456,"position":253,"raceTime":"00:29:07","ageGrading":51.06,"pb":true},{"event":"Rushmoor","date":"2018-11-03T00:00:00","eventNo":218,"position":316,"raceTime":"00:30:02","ageGrading":49.50,"pb":true},{"event":"Frimley Lodge","date":"2018-10-20T00:00:00","eventNo":452,"position":427,"raceTime":"00:36:21","ageGrading":40.90,"pb":true},{"event":"Rushmoor","date":"2018-09-29T00:00:00","eventNo":213,"position":91,"raceTime":"00:24:11","ageGrading":61.47,"pb":true},{"event":"Frimley Lodge","date":"2018-09-22T00:00:00","eventNo":448,"position":138,"raceTime":"00:24:18","ageGrading":61.18,"pb":true},{"event":"Bushy Park","date":"2018-09-15T00:00:00","eventNo":752,"position":410,"raceTime":"00:24:22","ageGrading":61.01,"pb":true},{"event":"Frimley Lodge","date":"2018-09-08T00:00:00","eventNo":446,"position":139,"raceTime":"00:24:36","ageGrading":60.43,"pb":true},{"event":"Frimley Lodge","date":"2018-09-01T00:00:00","eventNo":445,"position":134,"raceTime":"00:24:32","ageGrading":60.60,"pb":true},{"event":"Frimley Lodge","date":"2018-08-18T00:00:00","eventNo":443,"position":164,"raceTime":"00:24:37","ageGrading":60.39,"pb":true},{"event":"Frimley Lodge","date":"2018-08-11T00:00:00","eventNo":442,"position":180,"raceTime":"00:26:04","ageGrading":57.03,"pb":true},{"event":"Frimley Lodge","date":"2018-07-28T00:00:00","eventNo":441,"position":281,"raceTime":"00:27:46","ageGrading":53.54,"pb":true},{"event":"Exmouth","date":"2018-07-21T00:00:00","eventNo":30,"position":97,"raceTime":"00:25:13","ageGrading":58.96,"pb":true},{"event":"Frimley Lodge","date":"2018-07-14T00:00:00","eventNo":439,"position":486,"raceTime":"00:32:21","ageGrading":45.96,"pb":true},{"event":"Frimley Lodge","date":"2018-07-07T00:00:00","eventNo":438,"position":351,"raceTime":"00:29:03","ageGrading":51.18,"pb":true},{"event":"Frimley Lodge","date":"2018-06-23T00:00:00","eventNo":436,"position":424,"raceTime":"00:35:01","ageGrading":42.46,"pb":true},{"event":"Frimley Lodge","date":"2018-06-16T00:00:00","eventNo":435,"position":369,"raceTime":"00:31:48","ageGrading":46.75,"pb":true},{"event":"Rushmoor","date":"2017-09-02T00:00:00","eventNo":164,"position":285,"raceTime":"00:31:02","ageGrading":47.80,"pb":true},{"event":"Frimley Lodge","date":"2017-07-22T00:00:00","eventNo":389,"position":353,"raceTime":"00:30:06","ageGrading":49.28,"pb":true},{"event":"Frimley Lodge","date":"2017-07-15T00:00:00","eventNo":388,"position":357,"raceTime":"00:31:11","ageGrading":47.57,"pb":true},{"event":"Frimley Lodge","date":"2017-07-08T00:00:00","eventNo":387,"position":465,"raceTime":"00:34:17","ageGrading":43.27,"pb":true},{"event":"Rushmoor","date":"2017-06-24T00:00:00","eventNo":155,"position":326,"raceTime":"00:33:34","ageGrading":44.19,"pb":true},{"event":"Rushmoor","date":"2017-06-03T00:00:00","eventNo":152,"position":544,"raceTime":"00:36:24","ageGrading":40.75,"pb":true},{"event":"Rushmoor","date":"2017-05-06T00:00:00","eventNo":149,"position":364,"raceTime":"00:34:02","ageGrading":43.58,"pb":true},{"event":"Rushmoor","date":"2017-04-29T00:00:00","eventNo":148,"position":414,"raceTime":"00:35:40","ageGrading":41.59,"pb":true},{"event":"Rushmoor","date":"2017-04-08T00:00:00","eventNo":145,"position":166,"raceTime":"00:27:14","ageGrading":54.47,"pb":true},{"event":"Frimley Lodge","date":"2017-01-28T00:00:00","eventNo":366,"position":536,"raceTime":"00:48:42","ageGrading":30.42,"pb":true},{"event":"Frimley Lodge","date":"2017-01-14T00:00:00","eventNo":364,"position":336,"raceTime":"00:30:46","ageGrading":48.16,"pb":true},{"event":"Frimley Lodge","date":"2017-01-01T00:00:00","eventNo":362,"position":334,"raceTime":"00:34:11","ageGrading":43.34,"pb":true},{"event":"Woking","date":"2016-12-10T00:00:00","eventNo":117,"position":224,"raceTime":"00:57:16","ageGrading":25.87,"pb":true},{"event":"Rushmoor","date":"2016-12-03T00:00:00","eventNo":127,"position":168,"raceTime":"00:30:09","ageGrading":49.14,"pb":true},{"event":"Rushmoor","date":"2016-11-19T00:00:00","eventNo":125,"position":287,"raceTime":"00:43:15","ageGrading":34.26,"pb":true},{"event":"Frimley Lodge","date":"2016-10-29T00:00:00","eventNo":351,"position":304,"raceTime":"00:31:57","ageGrading":46.37,"pb":true},{"event":"Woking","date":"2016-09-03T00:00:00","eventNo":104,"position":195,"raceTime":"00:29:59","ageGrading":49.42,"pb":true},{"event":"Frimley Lodge","date":"2016-08-27T00:00:00","eventNo":342,"position":369,"raceTime":"00:33:38","ageGrading":44.05,"pb":true},{"event":"Frimley Lodge","date":"2016-08-13T00:00:00","eventNo":340,"position":385,"raceTime":"00:34:24","ageGrading":43.07,"pb":true},{"event":"Frimley Lodge","date":"2016-07-16T00:00:00","eventNo":337,"position":505,"raceTime":"00:38:54","ageGrading":38.09,"pb":true},{"event":"Frimley Lodge","date":"2016-05-21T00:00:00","eventNo":330,"position":380,"raceTime":"00:33:01","ageGrading":44.88,"pb":true},{"event":"Frimley Lodge","date":"2016-05-14T00:00:00","eventNo":329,"position":488,"raceTime":"00:55:09","ageGrading":26.87,"pb":true},{"event":"Frimley Lodge","date":"2016-05-07T00:00:00","eventNo":328,"position":422,"raceTime":"00:47:34","ageGrading":31.15,"pb":true},{"event":"Frimley Lodge","date":"2016-04-23T00:00:00","eventNo":327,"position":344,"raceTime":"00:33:08","ageGrading":44.72,"pb":true},{"event":"Frimley Lodge","date":"2016-01-23T00:00:00","eventNo":314,"position":306,"raceTime":"00:33:12","ageGrading":44.58,"pb":true},{"event":"Frimley Lodge","date":"2015-03-28T00:00:00","eventNo":271,"position":294,"raceTime":"00:27:33","ageGrading":53.72,"pb":true}]}